odoo/addons/delivery_date_exclude_service/README.rst
odoo/addons/delivery_date_exclude_service/__init__.py
odoo/addons/delivery_date_exclude_service/__manifest__.py
odoo/addons/delivery_date_exclude_service/i18n/delivery_date_exclude_service.pot
odoo/addons/delivery_date_exclude_service/i18n/it.po
odoo/addons/delivery_date_exclude_service/models/__init__.py
odoo/addons/delivery_date_exclude_service/models/product_template.py
odoo/addons/delivery_date_exclude_service/models/sale_order.py
odoo/addons/delivery_date_exclude_service/models/sale_order_line.py
odoo/addons/delivery_date_exclude_service/readme/CONFIGURE.md
odoo/addons/delivery_date_exclude_service/readme/CONTRIBUTORS.md
odoo/addons/delivery_date_exclude_service/readme/CREDITS.md
odoo/addons/delivery_date_exclude_service/readme/DESCRIPTION.md
odoo/addons/delivery_date_exclude_service/static/description/icon.png
odoo/addons/delivery_date_exclude_service/static/description/index.html
odoo/addons/delivery_date_exclude_service/tests/__init__.py
odoo/addons/delivery_date_exclude_service/tests/test_exclude_service.py
odoo/addons/delivery_date_exclude_service/views/product_views.xml
odoo_addon_delivery_date_exclude_service-18.0.1.0.0.4.dist-info/METADATA
odoo_addon_delivery_date_exclude_service-18.0.1.0.0.4.dist-info/WHEEL
odoo_addon_delivery_date_exclude_service-18.0.1.0.0.4.dist-info/top_level.txt
odoo_addon_delivery_date_exclude_service-18.0.1.0.0.4.dist-info/RECORD
